code_rag_agent/__init__.py
code_rag_agent/agent.py
code_rag_agent/cli.py
code_rag_agent/prompts.py
code_rag_agent/config/__init__.py
code_rag_agent/config/settings.py
code_rag_agent/llm_clients/__init__.py
code_rag_agent/llm_clients/base_client.py
code_rag_agent/llm_clients/openai_client.py
code_rag_agent/retrievers/__init__.py
code_rag_agent/retrievers/base_retriever.py
code_rag_agent/retrievers/pinecone_retriever.py
code_rag_agent-0.1.0.dist-info/licenses/LICENSE
code_rag_agent-0.1.0.dist-info/METADATA
code_rag_agent-0.1.0.dist-info/WHEEL
code_rag_agent-0.1.0.dist-info/entry_points.txt
code_rag_agent-0.1.0.dist-info/top_level.txt
code_rag_agent-0.1.0.dist-info/RECORD
