Metadata-Version: 2.4
Name: code-rag-agent
Version: 0.1.0
Summary: Production-ready RAG agent for intelligent code retrieval and question answering
Author-email: Sandeep G <sandeepg2890@gmail.com>
License: Apache-2.0
Project-URL: Homepage, https://github.com/sandeepgovi/code-rag-agent
Project-URL: Repository, https://github.com/sandeepgovi/code-rag-agent
Project-URL: Bug Tracker, https://github.com/sandeepgovi/code-rag-agent/issues
Keywords: rag,code-analysis,langchain,vector-store,ai,llm,retrieval
Classifier: Development Status :: 4 - Beta
Classifier: Intended Audience :: Developers
Classifier: License :: OSI Approved :: Apache Software License
Classifier: Programming Language :: Python :: 3
Classifier: Programming Language :: Python :: 3.9
Classifier: Programming Language :: Python :: 3.10
Classifier: Programming Language :: Python :: 3.11
Classifier: Programming Language :: Python :: 3.12
Classifier: Programming Language :: Python :: 3.13
Classifier: Topic :: Software Development :: Libraries :: Python Modules
Classifier: Topic :: Scientific/Engineering :: Artificial Intelligence
Requires-Python: >=3.9
License-File: LICENSE
Requires-Dist: pydantic>=2.0.0
Requires-Dist: python-dotenv>=1.0.0
Requires-Dist: pydantic_settings>=2.11.0
Requires-Dist: langchain>=0.1.0
Requires-Dist: langchain-community>=0.0.1
Requires-Dist: langchain-openai>=0.0.5
Requires-Dist: langchain-pinecone>=0.0.3
Requires-Dist: langchain-huggingface>=0.0.1
Requires-Dist: lark>=1.0.0
Requires-Dist: pinecone-client>=3.0.0
Requires-Dist: sentence-transformers>=2.0.0
Requires-Dist: einops>=0.6.0
Requires-Dist: click>=8.0.0
Provides-Extra: dev
Requires-Dist: pytest>=7.0.0; extra == "dev"
Requires-Dist: pytest-cov>=4.0.0; extra == "dev"
Requires-Dist: black>=23.0.0; extra == "dev"
Requires-Dist: ruff>=0.1.0; extra == "dev"
Dynamic: license-file
